[{"source":"JackManifoldTV","target":"tommyinnit","deltaViewers":9764},{"source":"Offline","target":"tommyinnit","deltaViewers":162129},{"source":"Philza","target":"Offline","deltaViewers":11329},{"source":"Offline","target":"Philza","deltaViewers":6090},{"source":"Offline","target":"CaptainPuffy","deltaViewers":3084},{"source":"Philza","target":"tommyinnit","deltaViewers":11544},{"source":"JackManifoldTV","target":"Offline","deltaViewers":5888},{"source":"HBomb94","target":"tommyinnit","deltaViewers":238},{"source":"Foolish__Gamers","target":"tommyinnit","deltaViewers":2250},{"source":"CaptainPuffy","target":"tommyinnit","deltaViewers":2355},{"source":"CaptainPuffy","target":"Offline","deltaViewers":1894},{"source":"Foolish__Gamers","target":"Offline","deltaViewers":1984},{"source":"Philza","target":"awesamdude","deltaViewers":432},{"source":"CaptainPuffy","target":"JackManifoldTV","deltaViewers":35},{"source":"CaptainPuffy","target":"Philza","deltaViewers":42},{"source":"JackManifoldTV","target":"CaptainPuffy","deltaViewers":144},{"source":"HBomb94","target":"Offline","deltaViewers":979},{"source":"JackManifoldTV","target":"Philza","deltaViewers":104},{"source":"JackManifoldTV","target":"awesamdude","deltaViewers":142},{"source":"Philza","target":"CaptainPuffy","deltaViewers":335},{"source":"CaptainPuffy","target":"Foolish__Gamers","deltaViewers":21},{"source":"CaptainPuffy","target":"awesamdude","deltaViewers":39},{"source":"Philza","target":"JackManifoldTV","deltaViewers":262},{"source":"HBomb94","target":"CaptainPuffy","deltaViewers":48},{"source":"HBomb94","target":"awesamdude","deltaViewers":223},{"source":"Foolish__Gamers","target":"awesamdude","deltaViewers":125},{"source":"Foolish__Gamers","target":"CaptainPuffy","deltaViewers":128},{"source":"Philza","target":"Foolish__Gamers","deltaViewers":75},{"source":"Foolish__Gamers","target":"JackManifoldTV","deltaViewers":94},{"source":"Foolish__Gamers","target":"Philza","deltaViewers":70},{"source":"HBomb94","target":"Philza","deltaViewers":34},{"source":"JackManifoldTV","target":"Foolish__Gamers","deltaViewers":48},{"source":"HBomb94","target":"Foolish__Gamers","deltaViewers":16},{"source":"HBomb94","target":"JackManifoldTV","deltaViewers":22},{"source":"Offline","target":"awesamdude","deltaViewers":1935},{"source":"Offline","target":"JackManifoldTV","deltaViewers":2353},{"source":"Offline","target":"Foolish__Gamers","deltaViewers":1232}]