[{"source":"Offline","target":"TubboLIVE","deltaViewers":11027},{"source":"Offline","target":"Philza","deltaViewers":14785},{"source":"TubboLIVE","target":"Philza","deltaViewers":1223},{"source":"Philza","target":"Offline","deltaViewers":14100},{"source":"TubboLIVE","target":"Offline","deltaViewers":9409},{"source":"Philza","target":"TubboLIVE","deltaViewers":1277},{"source":"Offline","target":"Foolish__Gamers","deltaViewers":3198},{"source":"Foolish__Gamers","target":"Offline","deltaViewers":2808},{"source":"Foolish__Gamers","target":"TubboLIVE","deltaViewers":313},{"source":"Foolish__Gamers","target":"Philza","deltaViewers":354},{"source":"TubboLIVE","target":"Foolish__Gamers","deltaViewers":238},{"source":"Philza","target":"Foolish__Gamers","deltaViewers":423},{"source":"HBomb94","target":"Offline","deltaViewers":731},{"source":"HBomb94","target":"TubboLIVE","deltaViewers":268},{"source":"Foolish__Gamers","target":"HBomb94","deltaViewers":11},{"source":"HBomb94","target":"Foolish__Gamers","deltaViewers":19},{"source":"Philza","target":"HBomb94","deltaViewers":36},{"source":"TubboLIVE","target":"HBomb94","deltaViewers":163},{"source":"HBomb94","target":"Philza","deltaViewers":63},{"source":"Offline","target":"HBomb94","deltaViewers":668}]