[{"source":"Tubbo","target":"RanbooLive","deltaViewers":30248},{"source":"Offline","target":"Nihachu","deltaViewers":1110},{"source":"Offline","target":"RanbooLive","deltaViewers":34266},{"source":"Nihachu","target":"Offline","deltaViewers":2729},{"source":"Offline","target":"CaptainPuffy","deltaViewers":4538},{"source":"Tubbo","target":"Offline","deltaViewers":36516},{"source":"Fundy","target":"Offline","deltaViewers":5078},{"source":"Tubbo","target":"CaptainPuffy","deltaViewers":1513},{"source":"Fundy","target":"RanbooLive","deltaViewers":621},{"source":"Tubbo","target":"Nihachu","deltaViewers":545},{"source":"Fundy","target":"CaptainPuffy","deltaViewers":342},{"source":"Nihachu","target":"RanbooLive","deltaViewers":646},{"source":"Fundy","target":"Nihachu","deltaViewers":35},{"source":"Nihachu","target":"CaptainPuffy","deltaViewers":162}]