[{"source":"HBomb94","target":"Offline","deltaViewers":806},{"source":"Fundy","target":"Offline","deltaViewers":5067},{"source":"Offline","target":"Fundy","deltaViewers":4671},{"source":"HBomb94","target":"Fundy","deltaViewers":140},{"source":"Offline","target":"HBomb94","deltaViewers":717},{"source":"Offline","target":"Foolish__Gamers","deltaViewers":6134},{"source":"Foolish__Gamers","target":"Offline","deltaViewers":6396},{"source":"Foolish__Gamers","target":"Fundy","deltaViewers":392},{"source":"Foolish__Gamers","target":"HBomb94","deltaViewers":39},{"source":"HBomb94","target":"Foolish__Gamers","deltaViewers":49},{"source":"Fundy","target":"Foolish__Gamers","deltaViewers":276},{"source":"Fundy","target":"HBomb94","deltaViewers":103}]