[{"source":"HBomb94","target":"Nihachu","deltaViewers":603},{"source":"Offline","target":"Nihachu","deltaViewers":24278},{"source":"Offline","target":"Fundy","deltaViewers":3997},{"source":"Foolish__Gamers","target":"Offline","deltaViewers":10531},{"source":"Foolish__Gamers","target":"Nihachu","deltaViewers":8633},{"source":"Offline","target":"HBomb94","deltaViewers":468},{"source":"Fundy","target":"Offline","deltaViewers":4269},{"source":"Fundy","target":"Nihachu","deltaViewers":1882},{"source":"Foolish__Gamers","target":"Fundy","deltaViewers":735},{"source":"HBomb94","target":"Offline","deltaViewers":839},{"source":"Foolish__Gamers","target":"HBomb94","deltaViewers":32},{"source":"HBomb94","target":"Fundy","deltaViewers":175},{"source":"Fundy","target":"HBomb94","deltaViewers":38}]