[{"source":"Offline","target":"hannahxxrose","deltaViewers":2718},{"source":"hannahxxrose","target":"Offline","deltaViewers":3335},{"source":"Michaelmcchill","target":"Offline","deltaViewers":2999},{"source":"hannahxxrose","target":"Michaelmcchill","deltaViewers":96},{"source":"hannahxxrose","target":"ranboobutnot","deltaViewers":315},{"source":"Michaelmcchill","target":"ranboobutnot","deltaViewers":173},{"source":"Michaelmcchill","target":"hannahxxrose","deltaViewers":43},{"source":"ranboobutnot","target":"Offline","deltaViewers":9319},{"source":"ranboobutnot","target":"Michaelmcchill","deltaViewers":276},{"source":"ranboobutnot","target":"hannahxxrose","deltaViewers":84},{"source":"Offline","target":"Michaelmcchill","deltaViewers":2042},{"source":"Offline","target":"ranboobutnot","deltaViewers":6282}]